{"origin": "http://wallbase.cc/wallpaper/56252", "download_link": "http://wallpapers.wallbase.cc/manga-anime/wallpaper-56252.jpg", "views": 29136, "x_resolution": 2276, "filetype": "jpg", "site": "wallbase.cc", "y_resolution": 2000, "colors": ["#000000", "#44afd9", "#fcecd7", "#f4cf3d", "#351c39"], "comments": [""], "favorites": 93, "descriptors": ["Death Note", "blondes", "stockings", "chibi", "Yagami Light", "L.", "big eyes", "anime", "Amane Misa", "anime girls", "black hair"], "uploader": " 4chan"}