{"origin": "http://wallbase.cc/wallpaper/3032230", "favorites": 37, "views": 12553, "x_resolution": 2000, "filetype": "png", "site": "wallbase.cc", "y_resolution": 1151, "colors": ["#000000"], "comments": [""], "download_link": "http://wallpapers.wallbase.cc/manga-anime/wallpaper-3032230.png", "descriptors": ["monsters", "demons", "artwork", "alternative"], "uploader": " Dulet"},
{"origin": "http://wallbase.cc/wallpaper/3032544", "favorites": 203, "views": 62833, "x_resolution": 1920, "filetype": "jpg", "site": "wallbase.cc", "y_resolution": 1080, "colors": ["#000000"], "comments": [""], "download_link": "http://wallpapers.wallbase.cc/rozne/wallpaper-3032544.jpg", "descriptors": ["dark", "glowing", "Noble M600", "sports car", "rear angle view"], "uploader": " seesalt"}